ssmtool/__init__.py
ssmtool/__main__.py
ssmtool/api.py
ssmtool/config.py
ssmtool/db.py
ssmtool/dictionary.py
ssmtool/dictmanager.py
ssmtool/forvo.py
ssmtool/main.py
ssmtool/tools.py
ssmtool/ext/__init__.py
ssmtool/ext/importer/KindleImporter.py
ssmtool/ext/importer/__init__.py
ssmtool/ext/reader/__init__.py
ssmtool/ext/reader/server.py
ssmtool/ext/reader/utils.py
ssmtool/ext/reader/static/bulma.min.css
ssmtool/ext/reader/static/jquery-3.6.0.min.js
ssmtool/ext/reader/static/lodash.min.js
ssmtool/ext/reader/templates/home.html
ssmtool/ext/reader/templates/layout.html
ssmtool/ext/reader/templates/page.html
ssmtool/ext/reader/templates/upload.html
ssmtool-0.6.4.data/data/share/applications/ssmtool.desktop
ssmtool-0.6.4.data/data/share/icons/ssmtool.png
ssmtool-0.6.4.dist-info/LICENSE
ssmtool-0.6.4.dist-info/METADATA
ssmtool-0.6.4.dist-info/WHEEL
ssmtool-0.6.4.dist-info/entry_points.txt
ssmtool-0.6.4.dist-info/top_level.txt
ssmtool-0.6.4.dist-info/RECORD
