Metadata-Version: 2.1
Name: ssmtool
Version: 0.6.4
Summary: A simple, effective sentence mining tool.
Home-page: https://github.com/FreeLanguageTools/ssmtool
Author: FreeLanguageTools
Author-email: shaoyu0209@tuta.io
License: UNKNOWN
Platform: UNKNOWN
Classifier: Programming Language :: Python :: 3
Classifier: License :: OSI Approved :: GNU General Public License v3 (GPLv3)
Classifier: Operating System :: OS Independent
Classifier: Environment :: X11 Applications :: Qt
Requires-Python: >=3.8
License-File: LICENSE
Requires-Dist: lxml
Requires-Dist: PyQt5
Requires-Dist: requests
Requires-Dist: beautifulsoup4
Requires-Dist: simplemma
Requires-Dist: pystardict
Requires-Dist: bidict
Requires-Dist: flask
Requires-Dist: flask-sqlalchemy
Requires-Dist: charset-normalizer
Requires-Dist: slpp
Requires-Dist: mobi
Requires-Dist: sentence-splitter
Requires-Dist: pymorphy2
Requires-Dist: pymorphy2-dicts
Requires-Dist: pymorphy2-dicts-ru
Requires-Dist: playsound
Requires-Dist: ebooklib
